mkdocs_windmill/404.html
mkdocs_windmill/__init__.py
mkdocs_windmill/article-nav.html
mkdocs_windmill/base.html
mkdocs_windmill/main.html
mkdocs_windmill/mkdocs_theme.yml
mkdocs_windmill/nav-item.html
mkdocs_windmill/nav-pane.html
mkdocs_windmill/page-nav-urls.html
mkdocs_windmill/repo-icon.html
mkdocs_windmill/search.html
mkdocs_windmill/topbar.html
mkdocs_windmill/css/base.css
mkdocs_windmill/css/bootstrap-3.3.7.css
mkdocs_windmill/css/bootstrap-3.3.7.min.css
mkdocs_windmill/css/font-awesome-4.7.0.css
mkdocs_windmill/css/font-awesome-4.7.0.min.css
mkdocs_windmill/css/highlight.css
mkdocs_windmill/fonts/fontawesome-webfont.eot
mkdocs_windmill/fonts/fontawesome-webfont.svg
mkdocs_windmill/fonts/fontawesome-webfont.ttf
mkdocs_windmill/fonts/fontawesome-webfont.woff
mkdocs_windmill/fonts/fontawesome-webfont.woff2
mkdocs_windmill/fonts/glyphicons-halflings-regular.eot
mkdocs_windmill/fonts/glyphicons-halflings-regular.svg
mkdocs_windmill/fonts/glyphicons-halflings-regular.ttf
mkdocs_windmill/fonts/glyphicons-halflings-regular.woff
mkdocs_windmill/fonts/glyphicons-halflings-regular.woff2
mkdocs_windmill/img/favicon.ico
mkdocs_windmill/img/logo.png
mkdocs_windmill/js/base.js
mkdocs_windmill/js/bootstrap-3.3.7.js
mkdocs_windmill/js/bootstrap-3.3.7.min.js
mkdocs_windmill/js/elasticlunr.js
mkdocs_windmill/js/elasticlunr.min.js
mkdocs_windmill/js/highlight.pack.js
mkdocs_windmill/js/jquery-3.2.1.js
mkdocs_windmill/js/jquery-3.2.1.min.js
mkdocs_windmill-1.0.5.dist-info/LICENSE
mkdocs_windmill-1.0.5.dist-info/METADATA
mkdocs_windmill-1.0.5.dist-info/WHEEL
mkdocs_windmill-1.0.5.dist-info/entry_points.txt
mkdocs_windmill-1.0.5.dist-info/top_level.txt
mkdocs_windmill-1.0.5.dist-info/RECORD
