Metadata-Version: 2.1
Name: mkdocs-windmill
Version: 1.0.5
Summary: MkDocs theme focused on navigation and usability
Home-page: https://github.com/gristlabs/mkdocs-windmill
Author: Dmitry S
Author-email: dmitry@getgrist.com
License: MIT
Platform: UNKNOWN
Classifier: Development Status :: 5 - Production/Stable
Classifier: License :: OSI Approved :: MIT License
Classifier: Topic :: Documentation
Classifier: Topic :: Text Processing
Requires-Dist: mkdocs
